{
  "generated_at": "2025-08-05T05:57:58.485595+08:00",
  "total_titles_processed": 315,
  "failed_sources": [],
  "trends": [
    {
      "keyword_group": "特朗普",
      "match_count": 8,
      "titles": [
        {
          "title": "特朗普怒斥“这是骗局”，两党人士都不干了",
          "url": "https://news.ifeng.com/c/8lXtL9hEARd",
          "source": "凤凰网",
          "ranks": [
            2
          ],
          "is_new": false,
          "appearance_count": 1,
          "time_info": ""
        },
        {
          "title": "美印关系现裂痕，莫迪呼吁推“国货”，印度无视特朗普威胁“坚持买俄油”",
          "url": "https://wallstreetcn.com/articles/3752549",
          "source": "华尔街见闻",
          "ranks": [
            6
          ],
          "is_new": false,
          "appearance_count": 1,
          "time_info": ""
        },
        {
          "title": "“悉尼妹”广告被批宣扬白人至上主义，特朗普却力挺(图)",
          "url": "https://news.ifeng.com/c/8lXv3stq2OQ",
          "source": "凤凰网",
          "ranks": [
            7
          ],
          "is_new": false,
          "appearance_count": 1,
          "time_info": ""
        },
        {
          "title": "下一任美联储主席本周揭晓？特朗普将在“未来几天”填补理事空位",
          "url": "https://wallstreetcn.com/articles/3752574",
          "source": "华尔街见闻",
          "ranks": [
            9
          ],
          "is_new": false,
          "appearance_count": 1,
          "time_info": ""
        },
        {
          "title": "特朗普带货广告点燃American Eagle股票涨势，分析师称出现迷因股色彩",
          "url": "https://wallstreetcn.com/livenews/2953346",
          "source": "华尔街见闻-快讯",
          "ranks": [
            10
          ],
          "is_new": false,
          "appearance_count": 1,
          "time_info": ""
        },
        {
          "title": "美特使或本周访俄，特朗普：周五前不停火就制裁俄罗斯",
          "url": "https://m.thepaper.cn/newsDetail_forward_31293820",
          "source": "澎湃新闻",
          "ranks": [
            18
          ],
          "is_new": false,
          "appearance_count": 1,
          "time_info": ""
        },
        {
          "title": "巴西股指涨幅扩大至0.36%，巴西雷亚尔兑美元涨0.6%。 巴西副总统称，贸易商会批准世贸组织关于美国关税的意见。 特朗普政府对巴西航空工业Embraer加征10%的关税仍然显得太高。 是否征求世贸组织的意见是总统卢拉的决定。 我们需要向美方表明，特朗普的关税缺乏经济方面的合理性。 我们正针对美国关税完成应急计划的制定工作，预计不会对巴西财政政策构成影响。",
          "url": "https://wallstreetcn.com/livenews/2953328",
          "source": "华尔街见闻-快讯",
          "ranks": [
            21
          ],
          "is_new": false,
          "appearance_count": 1,
          "time_info": ""
        },
        {
          "title": "印度硬刚特朗普：拒绝停购廉价俄油",
          "url": "https://www.toutiao.com/trending/7534535376002616878/",
          "source": "今日头条",
          "ranks": [
            23
          ],
          "is_new": false,
          "appearance_count": 1,
          "time_info": ""
        }
      ]
    },
    {
      "keyword_group": "美股",
      "match_count": 5,
      "titles": [
        {
          "title": "美股七巨头收盘播报｜周一（8月4日），美国科技股七巨头（Magnificent 7）指数涨2.04%，报183.46点。",
          "url": "https://wallstreetcn.com/livenews/2953356",
          "source": "华尔街见闻-快讯",
          "ranks": [
            1
          ],
          "is_new": true,
          "appearance_count": 1,
          "time_info": ""
        },
        {
          "title": "美联储降息预期升温，美股三大指数开盘齐升，欧股涨幅扩大，油价盘中跌超2%",
          "url": "https://wallstreetcn.com/articles/3752581",
          "source": "华尔街见闻",
          "ranks": [
            2
          ],
          "is_new": false,
          "appearance_count": 1,
          "time_info": ""
        },
        {
          "title": "金十图示：2025年08月04日（周一）热门中概股行情一览（美股收盘）",
          "url": "https://flash.jin10.com/detail/20250805041238134800",
          "source": "金十数据",
          "ranks": [
            17
          ],
          "is_new": false,
          "appearance_count": 1,
          "time_info": ""
        },
        {
          "title": "金十图示：2025年08月04日（周一）美股热门股票行情一览（美股收盘）",
          "url": "https://flash.jin10.com/detail/20250805041235427800",
          "source": "金十数据",
          "ranks": [
            18
          ],
          "is_new": false,
          "appearance_count": 1,
          "time_info": ""
        },
        {
          "title": "美股收盘：纳指涨近2% 英伟达涨3.6%",
          "url": "https://flash.jin10.com/detail/20250805040123091800",
          "source": "金十数据",
          "ranks": [
            28
          ],
          "is_new": false,
          "appearance_count": 1,
          "time_info": ""
        }
      ]
    },
    {
      "keyword_group": "美元",
      "match_count": 2,
      "titles": [
        {
          "title": "纽约期金涨超0.8%重拾3400美元关口，金银指数收涨将近4.5%",
          "url": "https://wallstreetcn.com/livenews/2953347",
          "source": "华尔街见闻-快讯",
          "ranks": [
            9
          ],
          "is_new": false,
          "appearance_count": 1,
          "time_info": ""
        },
        {
          "title": "周一（8月4日）纽约尾盘，ICE美元指数跌0.38%，报98.766点，日内交投区间为98.980-98.92点。 彭博美元指数跌0.37%，报1210.47点，日内交投区间为1212.14-1207.88点。",
          "url": "https://wallstreetcn.com/livenews/2953325",
          "source": "华尔街见闻-快讯",
          "ranks": [
            24
          ],
          "is_new": false,
          "appearance_count": 1,
          "time_info": ""
        }
      ]
    },
    {
      "keyword_group": "美债",
      "match_count": 1,
      "titles": [
        {
          "title": "周一（8月4日）纽约尾盘，美国10年期基准国债收益率跌2.35个基点，报4.1923%，日内交投于4.2552%-4.1904%区间。 两年期美债收益率跌0.65个基点，报3.6752%，日内交投于3.7265%-3.6550%区间。 02/10年期美债收益率利差跌1.503个基点，报+51.508个基点。",
          "url": "https://wallstreetcn.com/livenews/2953355",
          "source": "华尔街见闻-快讯",
          "ranks": [
            2
          ],
          "is_new": false,
          "appearance_count": 1,
          "time_info": ""
        }
      ]
    },
    {
      "keyword_group": "伊朗",
      "match_count": 1,
      "titles": [
        {
          "title": "美国国务院：国务卿鲁比奥今日与英国外交大臣拉米通话，讨论加沙、乌克兰、伊朗、苏丹问题。",
          "url": "https://flash.jin10.com/detail/20250805051805236800",
          "source": "金十数据",
          "ranks": [
            2
          ],
          "is_new": true,
          "appearance_count": 1,
          "time_info": ""
        }
      ]
    }
  ]
}